daskcheck
