Metadata-Version: 2.1
Name: daskcheck
Version: 0.0.14
Summary: Automatically created environment for python package
Home-page: http://gitlab.com/jaromrax/daskcheck
Author: jaromrax
Author-email: jaromrax@gmail.com
License: GPL2
Platform: UNKNOWN
